pydra/__init__.py
pydra/cli.py
pydra/config.py
pydra/parser.py
pydra/utils.py
pydra_config-0.16.0.dist-info/licenses/LICENSE
pydra_config-0.16.0.dist-info/METADATA
pydra_config-0.16.0.dist-info/WHEEL
pydra_config-0.16.0.dist-info/top_level.txt
pydra_config-0.16.0.dist-info/RECORD
