Metadata-Version: 2.4
Name: pydra-config
Version: 0.16.0
Summary: A flexible configuration library in pure Python
Home-page: https://github.com/jordan-benjamin/pydra
Author: Jordan Juravsky
License: Apache License 2.0
Classifier: Development Status :: 3 - Alpha
Classifier: Intended Audience :: Developers
Classifier: Programming Language :: Python :: 3.10
Requires-Python: >=3.10
License-File: LICENSE
Requires-Dist: PyYAML<7,>=6.0
Requires-Dist: dill<0.4,>=0.3.7
Requires-Dist: pydantic<3,>=2.9.2
Dynamic: author
Dynamic: classifier
Dynamic: description
Dynamic: description-content-type
Dynamic: home-page
Dynamic: license
Dynamic: license-file
Dynamic: requires-dist
Dynamic: requires-python
Dynamic: summary
